mcp_server_demo_9/__init__.py
mcp_server_demo_9/service.py
mcp_server_demo_9-0.4.0.dist-info/WHEEL
mcp_server_demo_9-0.4.0.dist-info/entry_points.txt
mcp_server_demo_9-0.4.0.dist-info/METADATA
mcp_server_demo_9-0.4.0.dist-info/RECORD
