Metadata-Version: 2.3
Name: mcp-server-demo-9
Version: 0.4.0
Summary: Add your description here
Author: tylnn68
Author-email: tylnn68 <11301536+tylnn68@user.noreply.gitee.com>
Requires-Dist: fastmcp>=0.1.0
Requires-Dist: mcp>=1.0.0
Requires-Python: >=3.10
